[
  {
    "title":"모험하는 아티스트와 콜렉터들의 놀이터",
    "name": {
      "kor":"페이퍼 그라운드",
      "eng":"paperground"
    },
    "desc": "페이퍼그라운드는 동시대 예술가들의 작업물을 다양한 루트로 선보이고 콜렉터와 연결하는 아트 커머스 에이전시(Art Commerce Agency)이자 온라인 편집샵(Collect Shop) 입니다. 자신만의 독특한 시선으로 작업을 이어가는 아티스트들, 그리고 이들의 시선과 작품에 공감하는 콜렉터들에게 페이퍼그라운드는 즐거운 놀이터이자 연결의 플랫폼이 되고자 합니다. 단순한 소비를 뛰어넘어 시선을 공유하고 교감하는 새로운 일상 예술 문화를 함께 만들어가기를 제안합니다.",
    "src": "/mini_logo.webp",
    "href": "https://www.instagram.com/paperground.kr/"
  },
  {
    "title":"아브리 아뜰리에",
    "name": {
      "kor":"Abri Atelier",
      "eng":"abriatelier"
    },
    "desc":" 아브리 아뜰리에는 불어로 안식처, 작업실이란 의미를 담고 있는 갤러리이자 미술 체험 공간입니다. 전라남도 장흥에 처음으로 생긴 Contemporary Art Gallery (동시대 예술 갤러리)로서 현존하는 작가들의 작품을 전시하는 공간입니다. 강아지 삼 형제와 아기 고양이가 함께 살고 있는 작은 카오스의 공간 아브리 아뜰리에는 2023년 9월에 오픈하여 지역민들에게 오늘날의 미술을 소개하고, 타 지역 예술가들과 만나는 현재진행형 공간입니다.아브리(안식처)라는 말이 나타내듯 방문하는 모든 분들에게 편안한 쉼의 공간이 되기를 지향합니다.",
    "src": "/JH_artists/aburi.png",
    "href": "https://www.instagram.com/abriatelier"
  }
]